{
    "1": 100,
    "2": 100,
    "3": 100,
    "4": 100,
    "5": 40,
    "6": 100,
    "7": 53,
    "8": 100,
    "9": 100,
    "10": 100,
    "11": 100,
    "12": 100,
    "13": 38,
    "14": 100,
    "15": 56,
    "16": 100,
    "17": 33,
    "18": 56,
    "19": 80,
    "20": 80,
    "21": 67,
    "22": 100,
    "23": 56,
    "24": 100,
    "25": 58,
    "26": 100,
    "27": 100,
    "28": 67,
    "29": 100,
    "30": 100,
    "31": 49,
    "32": 38,
    "33": 100,
    "34": 100,
    "35": 100,
    "36": 100,
    "37": 38,
    "38": 100,
    "39": 100,
    "40": 100,
    "41": 89,
    "42": 51,
    "43": 82,
    "44": 100,
    "45": 100,
    "46": 56,
    "47": 80,
    "48": 100,
    "49": 80,
    "50": 71,
    "51": 100,
    "52": 82,
    "53": 38,
    "54": 40,
    "55": 42,
    "56": 82,
    "57": 100,
    "58": 80,
    "59": 76,
    "60": 44,
    "61": 91,
    "62": 56,
    "63": 56,
    "64": 56,
    "65": 58,
    "66": 78,
    "67": 56,
    "68": 56,
    "69": 76,
    "70": 89,
    "71": 53,
    "72": 56,
    "73": 76,
    "74": 56,
    "75": 73,
    "76": 62,
    "77": 91,
    "78": 91,
    "79": 33,
    "80": 71,
    "81": 100,
    "82": 71,
    "83": 69,
    "84": 40,
    "85": 80,
    "86": 80,
    "87": 89,
    "88": 76,
    "89": 80,
    "90": 76,
    "91": 56,
    "92": 60,
    "93": 76,
    "94": 42,
    "95": 73,
    "96": 87,
    "97": 76,
    "98": 78,
    "99": 56,
    "100": 100,
    "average": 76.01
}